langevals_haystack/faithfulness.py
langevals_haystack/lib/common.py
langevals_haystack-0.1.4.dist-info/METADATA
langevals_haystack-0.1.4.dist-info/WHEEL
langevals_haystack-0.1.4.dist-info/RECORD
